azviz/__init__.py
azviz/cli.py
azviz/azure/__init__.py
azviz/azure/client.py
azviz/core/__init__.py
azviz/core/azviz.py
azviz/core/models.py
azviz/icons/__init__.py
azviz/icons/icon_manager.py
azviz/icons/azure_icons/General Service Icons/APIConnections.png
azviz/icons/azure_icons/General Service Icons/ApplicationGateway.png
azviz/icons/azure_icons/General Service Icons/AvailabilitySets.png
azviz/icons/azure_icons/General Service Icons/Connections.png
azviz/icons/azure_icons/General Service Icons/ContainerRegistries.png
azviz/icons/azure_icons/General Service Icons/DataFactories.png
azviz/icons/azure_icons/General Service Icons/DataLakeAnalytics.png
azviz/icons/azure_icons/General Service Icons/DiskSnapshots.png
azviz/icons/azure_icons/General Service Icons/Disks.png
azviz/icons/azure_icons/General Service Icons/EventHubClusters.png
azviz/icons/azure_icons/General Service Icons/EventHubs.png
azviz/icons/azure_icons/General Service Icons/FrontDoors.png
azviz/icons/azure_icons/General Service Icons/FunctionApps.png
azviz/icons/azure_icons/General Service Icons/KubernetesServices.png
azviz/icons/azure_icons/General Service Icons/LoadBalancers.png
azviz/icons/azure_icons/General Service Icons/LogAnalyticsWorkspaces.png
azviz/icons/azure_icons/General Service Icons/NetworkWatcher.png
azviz/icons/azure_icons/General Service Icons/ResourceGroups.png
azviz/icons/azure_icons/General Service Icons/Subscriptions.png
azviz/icons/azure_icons/General Service Icons/VMImages.png
azviz/icons/azure_icons/General Service Icons/appconfiguration.png
azviz/icons/azure_icons/General Service Icons/applicationinsights.png
azviz/icons/azure_icons/General Service Icons/appservices.png
azviz/icons/azure_icons/General Service Icons/automation.png
azviz/icons/azure_icons/General Service Icons/basics.png
azviz/icons/azure_icons/General Service Icons/cdnprofiles.png
azviz/icons/azure_icons/General Service Icons/containerinstances.png
azviz/icons/azure_icons/General Service Icons/cosmosdb.png
python_azviz-1.1.3.dist-info/licenses/LICENSE
python_azviz-1.1.3.dist-info/METADATA
python_azviz-1.1.3.dist-info/WHEEL
python_azviz-1.1.3.dist-info/entry_points.txt
python_azviz-1.1.3.dist-info/top_level.txt
python_azviz-1.1.3.dist-info/RECORD
