Metadata-Version: 2.4
Name: python-azviz
Version: 1.1.3
Summary: Azure resource topology visualization tool - Python implementation inspired by the PowerShell AzViz module
Author-email: Patrick Rutledge <rut31337@users.noreply.github.com>
License: MIT
Project-URL: Homepage, https://github.com/rut31337/python-azviz
Project-URL: Repository, https://github.com/rut31337/python-azviz
Project-URL: Documentation, https://github.com/rut31337/python-azviz#readme
Project-URL: Bug Tracker, https://github.com/rut31337/python-azviz/issues
Project-URL: Original PowerShell Version, https://github.com/PrateekKumarSingh/AzViz
Keywords: azure,visualization,topology,graph,cloud,infrastructure
Classifier: Development Status :: 3 - Alpha
Classifier: Intended Audience :: Developers
Classifier: Intended Audience :: System Administrators
Classifier: License :: OSI Approved :: MIT License
Classifier: Programming Language :: Python :: 3
Classifier: Programming Language :: Python :: 3.8
Classifier: Programming Language :: Python :: 3.9
Classifier: Programming Language :: Python :: 3.10
Classifier: Programming Language :: Python :: 3.11
Classifier: Programming Language :: Python :: 3.12
Classifier: Topic :: System :: Systems Administration
Classifier: Topic :: Software Development :: Libraries :: Python Modules
Requires-Python: >=3.8
License-File: LICENSE
Requires-Dist: azure-identity>=1.12.0
Requires-Dist: azure-mgmt-core>=1.4.0
Requires-Dist: azure-mgmt-resource>=23.0.0
Requires-Dist: azure-mgmt-network>=25.0.0
Requires-Dist: azure-mgmt-compute>=30.0.0
Requires-Dist: azure-mgmt-subscription>=3.1.1
Requires-Dist: networkx>=3.0
Requires-Dist: graphviz>=0.20.0
Requires-Dist: click>=8.0.0
Requires-Dist: pydantic>=2.0.0
Requires-Dist: rich>=13.0.0
Requires-Dist: jinja2>=3.0.0
Provides-Extra: dev
Requires-Dist: pytest>=7.0.0; extra == "dev"
Requires-Dist: pytest-cov>=4.0.0; extra == "dev"
Requires-Dist: black>=23.0.0; extra == "dev"
Requires-Dist: ruff>=0.1.0; extra == "dev"
Requires-Dist: mypy>=1.0.0; extra == "dev"
Requires-Dist: pre-commit>=3.0.0; extra == "dev"
Dynamic: license-file
